scada_data_analysis/__init__.py
scada_data_analysis/modules/__init__.py
scada_data_analysis/modules/power_curve_preprocessing.py
scada_data_analysis-1.0.3.dist-info/LICENSE
scada_data_analysis-1.0.3.dist-info/METADATA
scada_data_analysis-1.0.3.dist-info/WHEEL
scada_data_analysis-1.0.3.dist-info/top_level.txt
scada_data_analysis-1.0.3.dist-info/RECORD
