Metadata-Version: 2.1
Name: scada-data-analysis
Version: 1.0.3
Summary: A set of tools for enabling wind energy data analysis
Home-page: https://github.com/abbey2017/wind-energy-analytics
Author: Abiodun Olaoye
Author-email: abiodunolaoye8@gmail.com
License: UNKNOWN
Project-URL: Bug Tracker, https://github.com/abbey2017/wind-energy-analytics/issues
Keywords: power-curve-filtering,scada-data-analytics,wind-energy
Platform: UNKNOWN
Classifier: Programming Language :: Python :: 3
Classifier: License :: OSI Approved :: BSD License
Classifier: Operating System :: OS Independent
Requires-Python: >=3.6
License-File: LICENSE
Requires-Dist: pandas
Requires-Dist: matplotlib
